arm_preprocessing/__init__.py
arm_preprocessing/dataset.py
arm_preprocessing/discretisation.py
arm_preprocessing/squashing.py
arm_preprocessing/timeseries.py
arm_preprocessing-0.2.5.dist-info/LICENSE
arm_preprocessing-0.2.5.dist-info/METADATA
arm_preprocessing-0.2.5.dist-info/WHEEL
arm_preprocessing-0.2.5.dist-info/RECORD
