Metadata-Version: 2.1
Name: arm-preprocessing
Version: 0.2.5
Summary: Implementation of several preprocessing techniques for Association Rule Mining (ARM)
Home-page: https://github.com/firefly-cpp/arm-preprocessing
Keywords: association rule mining,data science,preprocessing
Author: Tadej Lahovnik
Author-email: tadej.lahovnik1@um.si
Requires-Python: >=3.9,<3.14
Classifier: Programming Language :: Python :: 3
Classifier: Programming Language :: Python :: 3.9
Classifier: Programming Language :: Python :: 3.10
Classifier: Programming Language :: Python :: 3.11
Classifier: Programming Language :: Python :: 3.12
Provides-Extra: docs
Provides-Extra: sport-activities-features
Requires-Dist: niaarm (>=0.4.1,<0.5.0)
Requires-Dist: pandas (>=2.1.1,<3.0.0)
Requires-Dist: scikit-learn (>=1.3.2,<2.0.0)
Requires-Dist: sport-activities-features (>=0.5.0,<0.6.0) ; extra == "sport-activities-features"
Project-URL: Documentation, http://arm-preprocessing.readthedocs.io
Project-URL: Repository, https://github.com/firefly-cpp/arm-preprocessing
